face_pro
