Metadata-Version: 1.0
Name: face-pro
Version: 0.0.3
Summary: face pro
Home-page: https://github.com/reventhao/face_pro/tree/master/face_pro
Author: reventhao
Author-email: ren895873@gmail.com
License: MIT Licence
Keywords: face_pro
Platform: any
